LICENSE.md
MANIFEST.in
README.md
requirements.txt
setup.py
epi2melabs/__init__.py
epi2melabs/notebook.py
epi2melabs/ping.py
epi2melabs.egg-info/PKG-INFO
epi2melabs.egg-info/SOURCES.txt
epi2melabs.egg-info/dependency_links.txt
epi2melabs.egg-info/entry_points.txt
epi2melabs.egg-info/not-zip-safe
epi2melabs.egg-info/requires.txt
epi2melabs.egg-info/top_level.txt
epi2melabs/workflows/__init__.py
epi2melabs/workflows/database.py
epi2melabs/workflows/docs.py
epi2melabs/workflows/invoke.py
epi2melabs/workflows/launcher.py
scripts/concatenate_fastqs
scripts/rationalise_fastq
scripts/rationalize_fastq
scripts/run
scripts/seqkit_bam_yaml